{"id": "t5_2tand_t3_majxxd_t1_grsx0ux", "creation": 1616415395, "origin": "t5_2tand_t3_majxxd", "height": 1, "replied_to": "t5_2tand_t3_majxxd", "down_vote": 0, "up_vote": 3, "social_network": "reddit", "replies_charged": false, "no_replies": false, "user": "casklord", "text": "Good for you man!\n\nJust because they are family doesn't mean you have to put up with them (if they don't act like family).\n\nIt's so important that you don't stretch yourself too thin helping anyone and everyone", "permalink": "/r/DecidingToBeBetter/comments/majxxd/im_going_to_stop_giving_financial_advice_and_help/grsx0ux/"}