{"id": "t5_2tand_t3_hrmsma_t1_fy8ki74", "creation": 1594892641, "origin": "t5_2tand_t3_hrmsma", "height": 1, "replied_to": "t5_2tand_t3_hrmsma", "down_vote": 0, "up_vote": 2, "social_network": "reddit", "replies_charged": false, "no_replies": false, "user": null, "text": "I've started journaling my days as well, to track/facilitate my improvement. Could you elaborate on your weekly habit tracker? And where do you normally keep your go-to quotes that help you? Thanks.", "permalink": "/r/DecidingToBeBetter/comments/hrmsma/17f_finally_quit_smoking_and_toxic_friends/fy8ki74/"}