{"id": "t5_2tand_t3_gfd9y7_t1_fptudt1", "creation": 1588898452, "origin": "t5_2tand_t3_gfd9y7", "height": 1, "replied_to": "t5_2tand_t3_gfd9y7", "down_vote": 0, "up_vote": 7, "social_network": "reddit", "replies_charged": false, "no_replies": false, "user": "slwrthnu_again", "text": "As someone else who was kicked out of college for having shit grades, went back, graduated, went to law school, graduated, and am now a practicing attorney. Kick ass! Good luck.", "permalink": "/r/DecidingToBeBetter/comments/gfd9y7/a_decade_ago_i_was_kicked_out_of_college_with_a/fptudt1/"}