{"id": "t5_2tand_t3_q4f2tk_t1_hfzy0ep", "creation": 1633797599, "origin": "t5_2tand_t3_q4f2tk", "height": 1, "replied_to": "t5_2tand_t3_q4f2tk", "down_vote": 0, "up_vote": 1, "social_network": "reddit", "replies_charged": false, "no_replies": false, "user": "XenaDazzlecheeks", "text": "I did not have my first son until I was in my 30s. I  am happy I waited until my 30s. You are still in your youth, go ask a girl out, talk to people, make connections and let yourself give and receive from those around you. I am 32 now and mentally feel 21. \n\nYou could benefit from counselling sessions and maybe its time to find a hobby to enjoy. Video games is simple and abundant and as a programmer you could make an easy transition into PCgaming, or perhaps its time to try something completely new and strange. It's your life, and you have, statistically speaking, another 40 to 50 years to go; go out and really seize the remaining years.", "permalink": "/r/DecidingToBeBetter/comments/q4f2tk/my_wasted_youth_please_dont_make_the_same_mistake/hfzy0ep/"}