{"id": "t5_2qpzs_t3_pwquw3", "request": ["5f7c2841-3f43-4682-8126-88825da57933", "5f467b61-8d4f-49ce-8264-8a9864cde71f"], "text": "Can we stop this narrative? like no, I just dont want to do anything. I don't want to work. I dont want to just stay home either. I dont want to go to school. like yeah im mentally ill but im not in any particular pain? i just dont feel like doing anything and i dont want to be homeless either so im just biding my time till I can move and get access to a gun.", "url": "https://www.reddit.com/r/SuicideWatch/comments/pwquw3/suicidal_people_just_want_the_pain_to_stop/", "title": "\"Suicidal people just want the pain to stop\"", "social_network": "reddit", "user": "BearComplex20", "subreddit": "SuicideWatch", "subreddit_path": "r/SuicideWatch/", "up_vote": 129, "down_vote": 0, "creation": 1632777505, "permalink": "/r/SuicideWatch/comments/pwquw3/suicidal_people_just_want_the_pain_to_stop/", "nsfw": false, "first_save": 1635421088.76308, "replies_charged": false}