{"id": "t5_2qh5i_t3_90yj68_t1_e2ujjl2", "creation": 1532290786, "origin": "t5_2qh5i_t3_90yj68", "height": 1, "replied_to": "t5_2qh5i_t3_90yj68", "down_vote": 0, "up_vote": 1, "social_network": "reddit", "replies_charged": false, "no_replies": false, "user": "RastaYJZ", "text": "It's so depressing actually, the movie industry today I mean, my main theme today was \"Old Vs New\" and used Steven as an example, I really hope I could meet him someday but I live so far and my field of work is vastly different, fingers crossed tho", "permalink": "/r/happy/comments/90yj68/faced_one_of_my_few_fears_today_and_gave_a/e2ujjl2/"}