{"id": "t5_2qh1i_t3_4e8oip_t1_d230hti", "creation": 1460663101, "origin": "t5_2qh1i_t3_4e8oip", "height": 1, "replied_to": "t5_2qh1i_t3_4e8oip", "down_vote": 0, "up_vote": 1, "social_network": "reddit", "replies_charged": false, "no_replies": false, "user": null, "text": "You're just not capable of a response, or maybe it is too many words for you, you sure as hell don't come across as anything above below average intelligence... ", "permalink": "/r/AskReddit/comments/4e8oip/serious_suicide_survivors_of_reddit_what_was_your/d230hti/"}