{"id": "t5_2qh1i_t3_4e8oip_t1_d1y679m", "creation": 1460354696, "origin": "t5_2qh1i_t3_4e8oip", "height": 1, "replied_to": "t5_2qh1i_t3_4e8oip", "down_vote": 0, "up_vote": 5, "social_network": "reddit", "replies_charged": false, "no_replies": false, "user": null, "text": "Question, here. If you are in severe pain always, what is the problem in becoming addicted to pain meds? How do you know you're addicted, and not just addicted to being pain free? I have no experience in this field at all.", "permalink": "/r/AskReddit/comments/4e8oip/serious_suicide_survivors_of_reddit_what_was_your/d1y679m/"}