{"id": "t5_2tand_t3_mi3a63_t1_gt2r3zz", "creation": 1617312200, "origin": "t5_2tand_t3_mi3a63", "height": 1, "replied_to": "t5_2tand_t3_mi3a63", "down_vote": 0, "up_vote": 1, "social_network": "reddit", "replies_charged": false, "no_replies": false, "user": "OlinSina", "text": "I have read Atomic habits, but I did not get the ideas you have put fourth out of it. I will do what I can to do what you have suggested.", "permalink": "/r/DecidingToBeBetter/comments/mi3a63/i_want_to_be_more_disciplined_just_maybe_not_as/gt2r3zz/"}