{"created_at": "Fri Dec 13 04:52:43 +0000 2019", "id": 1205349807193239553, "id_str": "1205349807193239553", "text": "RT @janbaker97: @Chrisballingall Wales will more than likely campaign to leave the Union &amp; join the EU as an independent country, once peop\u2026", "source": "<a href=\"http://twitter.com/download/iphone\" rel=\"nofollow\">Twitter for iPhone</a>", "truncated": false, "in_reply_to_status_id": null, "in_reply_to_status_id_str": null, "in_reply_to_user_id": null, "in_reply_to_user_id_str": null, "in_reply_to_screen_name": null, "geo": null, "coordinates": null, "place": null, "contributors": null, "retweeted_status": {"created_at": "Fri Dec 13 04:43:48 +0000 2019", "id": 1205347566386401282, "id_str": "1205347566386401282", "text": "@Chrisballingall Wales will more than likely campaign to leave the Union &amp; join the EU as an independent country, o\u2026 https://t.co/Zw1IOFW7fn", "display_text_range": [17, 140], "source": "<a href=\"http://twitter.com/download/android\" rel=\"nofollow\">Twitter for Android</a>", "truncated": true, "in_reply_to_status_id": 1205345290607300609, "in_reply_to_status_id_str": "1205345290607300609", "in_reply_to_user_id": 21060055, "in_reply_to_user_id_str": "21060055", "in_reply_to_screen_name": "Chrisballingall", "user": {"id": 451601582, "id_str": "451601582", "name": "Not Luna Lovegood 3.5% \ud83d\udda4 \ud83c\udf3f\ud83c\udff4\udb40\udc67\udb40\udc62\udb40\udc77\udb40\udc6c\udb40\udc73\udb40\udc7f \ud83c\udfaa\ud83c\uddea\ud83c\uddfa", "screen_name": "LunaNotreally", "location": "Wales, United Kingdom", "url": null, "description": "Back to protecting my identity from trolls. Pro-European.", "translator_type": "none", "protected": false, "verified": false, "followers_count": 5739, "friends_count": 5107, "listed_count": 40, "favourites_count": 37276, "statuses_count": 61165, "created_at": "Sat Dec 31 18:56:05 +0000 2011", "utc_offset": null, "time_zone": null, "geo_enabled": true, "lang": null, "contributors_enabled": false, "is_translator": false, "profile_background_color": "EDECE9", "profile_background_image_url": "http://abs.twimg.com/images/themes/theme16/bg.gif", "profile_background_image_url_https": "https://abs.twimg.com/images/themes/theme16/bg.gif", "profile_background_tile": true, "profile_link_color": "1B95E0", "profile_sidebar_border_color": "FFFFFF", "profile_sidebar_fill_color": "DDFFCC", "profile_text_color": "333333", "profile_use_background_image": true, "profile_image_url": "http://pbs.twimg.com/profile_images/1294310591025369088/eFqEzsfq_normal.jpg", "profile_image_url_https": "https://pbs.twimg.com/profile_images/1294310591025369088/eFqEzsfq_normal.jpg", "profile_banner_url": "https://pbs.twimg.com/profile_banners/451601582/1597423212", "default_profile": false, "default_profile_image": false, "following": null, "follow_request_sent": null, "notifications": null}, "geo": null, "coordinates": null, "place": null, "contributors": null, "is_quote_status": false, "extended_tweet": {"full_text": "@Chrisballingall Wales will more than likely campaign to leave the Union &amp; join the EU as an independent country, once people realise they've literally just committed economic suicide. It'll take a while though. Lots of people on my Facebook will be celebrating tomorrow. Just can't cure stupid.", "display_text_range": [17, 299], "entities": {"hashtags": [], "urls": [], "user_mentions": [{"screen_name": "Chrisballingall", "name": "Chris Ballingall \ud83c\udff4\udb40\udc67\udb40\udc62\udb40\udc73\udb40\udc63\udb40\udc74\udb40\udc7f\ud83c\uddea\ud83c\uddfa\ud83c\udff3\ufe0f\u200d\ud83c\udf08 #FBPA", "id": 21060055, "id_str": "21060055", "indices": [0, 16]}], "symbols": []}}, "quote_count": 0, "reply_count": 4, "retweet_count": 7, "favorite_count": 21, "entities": {"hashtags": [], "urls": [{"url": "https://t.co/Zw1IOFW7fn", "expanded_url": "https://twitter.com/i/web/status/1205347566386401282", "display_url": "twitter.com/i/web/status/1\u2026", "indices": [121, 144]}], "user_mentions": [{"screen_name": "Chrisballingall", "name": "Chris Ballingall \ud83c\udff4\udb40\udc67\udb40\udc62\udb40\udc73\udb40\udc63\udb40\udc74\udb40\udc7f\ud83c\uddea\ud83c\uddfa\ud83c\udff3\ufe0f\u200d\ud83c\udf08 #FBPA", "id": 21060055, "id_str": "21060055", "indices": [0, 16]}], "symbols": []}, "favorited": false, "retweeted": false, "filter_level": "low", "lang": "en"}, "is_quote_status": false, "quote_count": 0, "reply_count": 0, "retweet_count": 0, "favorite_count": 0, "entities": {"hashtags": [], "urls": [], "user_mentions": [{"screen_name": "janbaker97", "name": null, "id": null, "id_str": null, "indices": [3, 14]}, {"screen_name": "Chrisballingall", "name": "Chris Ballingall \ud83c\udff4\udb40\udc67\udb40\udc62\udb40\udc73\udb40\udc63\udb40\udc74\udb40\udc7f\ud83c\uddea\ud83c\uddfa\ud83c\udff3\ufe0f\u200d\ud83c\udf08 #FBPA", "id": 21060055, "id_str": "21060055", "indices": [16, 32]}], "symbols": []}, "favorited": false, "retweeted": false, "filter_level": "low", "lang": "en", "matching_rules": [{"tag": null}], "user_id": 389972564, "critic_word": "suicide once more", "user_information": {"id": 389972564, "id_str": "389972564", "name": "Dr Peter Dilworth \ud83d\udc99 #FBPE #GTTO 3.5% \ud83d\ude37", "screen_name": "PeterDilworth1", "location": null, "url": null, "description": "NHS GP, recently struck back on register. Hate inequality. Seriously anti Brexit Johnson Tories & Trump. Socialist. #Resist #StopBrexit #FBR #3point5percent", "translator_type": "none", "protected": false, "verified": false, "followers_count": 11715, "friends_count": 12765, "listed_count": 81, "favourites_count": 382678, "statuses_count": 267714, "created_at": "Thu Oct 13 08:21:40 +0000 2011", "utc_offset": null, "time_zone": null, "geo_enabled": false, "lang": null, "contributors_enabled": false, "is_translator": false, "profile_background_color": "C0DEED", "profile_background_image_url": "http://abs.twimg.com/images/themes/theme1/bg.png", "profile_background_image_url_https": "https://abs.twimg.com/images/themes/theme1/bg.png", "profile_background_tile": false, "profile_link_color": "1DA1F2", "profile_sidebar_border_color": "C0DEED", "profile_sidebar_fill_color": "DDEEF6", "profile_text_color": "333333", "profile_use_background_image": true, "profile_image_url": "http://pbs.twimg.com/profile_images/1231651106410897408/-ir8gxFU_normal.jpg", "profile_image_url_https": "https://pbs.twimg.com/profile_images/1231651106410897408/-ir8gxFU_normal.jpg", "profile_banner_url": "https://pbs.twimg.com/profile_banners/389972564/1580417536", "default_profile": true, "default_profile_image": false, "following": null, "follow_request_sent": null, "notifications": null}}