{"id": "t5_2tand_t3_or0633_t1_h6fbfhu", "creation": 1627174577, "origin": "t5_2tand_t3_or0633", "height": 1, "replied_to": "t5_2tand_t3_or0633", "down_vote": 0, "up_vote": 37, "social_network": "reddit", "replies_charged": false, "no_replies": false, "user": "Mouthtuom", "text": "Almost nobody is as accomplished at 25 as they want to be. Maybe set a doable goal for yourself, but it\u2019s good that you are enjoying life. Never let anyone take that away from you.", "permalink": "/r/DecidingToBeBetter/comments/or0633/i_dont_know_how_to_mature/h6fbfhu/"}