{"created_at": "Tue Dec 15 20:57:53 +0000 2020", "id": 1338951437154463746, "id_str": "1338951437154463746", "text": "@yuuribuns @gangslater @b7obs I\u2019m a week away from being diagnosed with adhd that led to depression anxiety and ocd\u2026 https://t.co/wh9yot9Iei", "display_text_range": [30, 140], "source": "<a href=\"http://twitter.com/download/iphone\" rel=\"nofollow\">Twitter for iPhone</a>", "truncated": true, "in_reply_to_status_id": 1338886711674368001, "in_reply_to_status_id_str": "1338886711674368001", "in_reply_to_user_id": 1316790608283996160, "in_reply_to_user_id_str": "1316790608283996160", "in_reply_to_screen_name": "yuuribuns", "geo": null, "coordinates": null, "place": null, "contributors": null, "is_quote_status": false, "extended_tweet": {"full_text": "@yuuribuns @gangslater @b7obs I\u2019m a week away from being diagnosed with adhd that led to depression anxiety and ocd or I just have depression anxiety and ocd. Just cause I don\u2019t have my diagnosis yet doesn\u2019t mean I don\u2019t pick at my eye brow till it bleeds or I can\u2019t get out of bed most days because of them", "display_text_range": [30, 307], "entities": {"hashtags": [], "urls": [], "user_mentions": [{"screen_name": "yuuribuns", "name": "nana \u2661", "id": 1316790608283996160, "id_str": "1316790608283996160", "indices": [0, 10]}, {"screen_name": "gangslater", "name": "slater", "id": 319679665, "id_str": "319679665", "indices": [11, 22]}, {"screen_name": "b7obs", "name": "max", "id": 1299121581709561856, "id_str": "1299121581709561856", "indices": [23, 29]}], "symbols": []}}, "quote_count": 0, "reply_count": 1, "retweet_count": 0, "favorite_count": 2, "entities": {"hashtags": [], "urls": [{"url": "https://t.co/wh9yot9Iei", "expanded_url": "https://twitter.com/i/web/status/1338951437154463746", "display_url": "twitter.com/i/web/status/1\u2026", "indices": [117, 140]}], "user_mentions": [{"screen_name": "yuuribuns", "name": "nana \u2661", "id": 1316790608283996160, "id_str": "1316790608283996160", "indices": [0, 10]}, {"screen_name": "gangslater", "name": "slater", "id": 319679665, "id_str": "319679665", "indices": [11, 22]}, {"screen_name": "b7obs", "name": "max", "id": 1299121581709561856, "id_str": "1299121581709561856", "indices": [23, 29]}], "symbols": []}, "favorited": false, "retweeted": false, "filter_level": "low", "lang": "en", "matching_rules": [{"tag": null}], "user_id": 1335579904335818753, "critic_word": "i diagnosed OCD", "user_information": {"id": 1335579904335818753, "id_str": "1335579904335818753", "name": "bibble", "screen_name": "bibblecanteat", "location": "\ud83c\udde8\ud83c\udde6122", "url": null, "description": "EDtwt//20//she/her//bisexual anorexic bitch//sw 175//ugw 100/DNF if not edtwt//ouid\ud83d\ude19\ud83d\udca8//no minors", "translator_type": "none", "protected": false, "verified": false, "followers_count": 363, "friends_count": 424, "listed_count": 1, "favourites_count": 2422, "statuses_count": 2082, "created_at": "Sun Dec 06 13:40:51 +0000 2020", "utc_offset": null, "time_zone": null, "geo_enabled": false, "lang": null, "contributors_enabled": false, "is_translator": false, "profile_background_color": "F5F8FA", "profile_background_image_url": "", "profile_background_image_url_https": "", "profile_background_tile": false, "profile_link_color": "1DA1F2", "profile_sidebar_border_color": "C0DEED", "profile_sidebar_fill_color": "DDEEF6", "profile_text_color": "333333", "profile_use_background_image": true, "profile_image_url": "http://pbs.twimg.com/profile_images/1335580586430373889/2oKAAU1t_normal.jpg", "profile_image_url_https": "https://pbs.twimg.com/profile_images/1335580586430373889/2oKAAU1t_normal.jpg", "profile_banner_url": "https://pbs.twimg.com/profile_banners/1335579904335818753/1607293682", "default_profile": true, "default_profile_image": false, "following": null, "follow_request_sent": null, "notifications": null}}