{"id": "t5_2tand_t3_lcu54p_t1_gm4519f", "creation": 1612533300, "origin": "t5_2tand_t3_lcu54p", "height": 1, "replied_to": "t5_2tand_t3_lcu54p", "down_vote": 0, "up_vote": 3, "social_network": "reddit", "replies_charged": false, "no_replies": false, "user": "AhahaNiceOne", "text": "Proud of you. Takes courage to do this. Therapy is one of the best things in my life right now. It makes 2 years since I started getting help and I don't regret anything. I'm a much better person now with less issues because of it. It really works. Hope the same goes for you. Wish you the best.", "permalink": "/r/DecidingToBeBetter/comments/lcu54p/tomorrow_is_my_first_day_of_therapy_ever/gm4519f/"}