{"id": "t5_2qh1i_t3_2dpvdz_t1_cjryhgx", "creation": 1408204321, "origin": "t5_2qh1i_t3_2dpvdz", "height": 1, "replied_to": "t5_2qh1i_t3_2dpvdz", "down_vote": 0, "up_vote": 2, "social_network": "reddit", "replies_charged": false, "no_replies": false, "user": null, "text": "Thanks, and yeah I'm doing much better. I have a boyfriend who is significantly less hob knob-y, and haven't attempted or even self-harmed in a good 8 months.", "permalink": "/r/AskReddit/comments/2dpvdz/serious_suicide_survivors_of_reddit_what_are_your/cjryhgx/"}