{"id": "t5_2tand_t3_cgbirz_t1_euh18oc", "creation": 1563818953, "origin": "t5_2tand_t3_cgbirz", "height": 1, "replied_to": "t5_2tand_t3_cgbirz", "down_vote": 0, "up_vote": 4, "social_network": "reddit", "replies_charged": false, "no_replies": false, "user": "seacookie89", "text": "Naw it's the wealthy flaunting their privilege to us plebs. Who tf gets $800 ALLOWANCE every month to spend as they please?", "permalink": "/r/DecidingToBeBetter/comments/cgbirz/i_started_saving_100week_every_week_since_june/euh18oc/"}