{"id": "t5_2tand_t3_ml398i_t1_gtk8vcm", "creation": 1617712129, "origin": "t5_2tand_t3_ml398i", "height": 1, "replied_to": "t5_2tand_t3_ml398i", "down_vote": 0, "up_vote": 11, "social_network": "reddit", "replies_charged": false, "no_replies": false, "user": "Cataclystic", "text": "If you need any help with fiber design send me a message, its really easy to catch on but some companies do it differently than others, but all have the same idea. Don't be nervous!! you got this! and thank you for reading!", "permalink": "/r/DecidingToBeBetter/comments/ml398i/i_quit_an_abusive_job_and_now_normal_jobs_seem/gtk8vcm/"}