{"id": "t5_2qh5i_t3_8hixuk_t1_dyknc0i", "creation": 1525671865, "origin": "t5_2qh5i_t3_8hixuk", "height": 1, "replied_to": "t5_2qh5i_t3_8hixuk", "down_vote": 0, "up_vote": 1, "social_network": "reddit", "replies_charged": false, "no_replies": false, "user": "kraebcakes", "text": "Thanks for the advice! We\u2019re pretty great at telling each other how much we appreciate one another, but I\u2019ll remember to make it intentional. ", "permalink": "/r/happy/comments/8hixuk/finally_found_my_person_after_what_feels_like_an/dyknc0i/"}