{"id": "t5_2qh5i_t3_knxsin", "request": ["e9d5c1b3-4f2e-427b-a98e-af434f9cf1da"], "text": "", "url": "https://i.redd.it/xv0xzuf34l861.jpg", "title": "My friends and I were gifted medals for artistic excellence in recognition of the virtual world we created for this year's Burning Man in the Multiverse", "social_network": "reddit", "user": "brianswichkow", "subreddit": "happy", "subreddit_path": "r/happy/", "up_vote": 201, "down_vote": 0, "creation": 1609447778, "permalink": "/r/happy/comments/knxsin/my_friends_and_i_were_gifted_medals_for_artistic/", "nsfw": false, "first_save": 1635441114.9385421, "replies_charged": false}