{"id": "t5_2tand_t3_n4ljjb_t1_gx08gez", "creation": 1620204969, "origin": "t5_2tand_t3_n4ljjb", "height": 1, "replied_to": "t5_2tand_t3_n4ljjb", "down_vote": 0, "up_vote": 2, "social_network": "reddit", "replies_charged": false, "no_replies": false, "user": "daneurl", "text": "Wow, totally amazing and thank you for sharing something so honest and true. I\u2019ve had moments of darkness but nothing like yours. I can see how painful it must have been and somehow you\u2019ve come through it. Thanks again.", "permalink": "/r/DecidingToBeBetter/comments/n4ljjb/after_drowning_in_depression_ptsd_and_addiction/gx08gez/"}